LICENSE
setup.py
fcp/__init__.py
fcp/fcp.py
fcp_xai.egg-info/PKG-INFO
fcp_xai.egg-info/SOURCES.txt
fcp_xai.egg-info/dependency_links.txt
fcp_xai.egg-info/requires.txt
fcp_xai.egg-info/top_level.txt